ringcounter.v
module ringcounter (input  clk, output reg [8:1]out);
    initial 
        begin
            
            out[7:1]=7'b0;
            out[8]=1'b1;

        end
    always @(posedge clk)
        begin
            out[8:2]<=out[7:1];//left shift
            out[1]<=out[8];
        end
    
endmodule

ringcountertb.v
`timescale  1ns/10ps
module ringcountertb;
wire [8:1]out;reg clk;

    ringcounter r1(.clk(clk),.out(out));
    initial begin
        clk<=0;
    forever 
    begin
        #5 clk = ~clk;
    end
    end
    initial begin
    $monitor("time: %2t clk=%b out=%b",$time,clk,out);
    $dumpfile("ringcountertb.vcd");
    $dumpvars(0,ringcountertb); 
    #200 $finish;
    end

endmodule

ringcountertb.vcd
$date
	Sat May 09 17:33:40 2026
$end
$version
	Icarus Verilog
$end
$timescale
	10ps
$end
$scope module ringcountertb $end
$var wire 8 ! out [8:1] $end
$var reg 1 " clk $end
$scope module r1 $end
$var wire 1 " clk $end
$var reg 8 # out [8:1] $end
$upscope $end
$upscope $end
$enddefinitions $end
$comment Show the parameter values. $end
$dumpall
$end
#0
$dumpvars
b10000000 #
0"
b10000000 !
$end
#500
b1 !
b1 #
1"
#1000
0"
#1500
b10 !
b10 #
1"
#2000
0"
#2500
b100 !
b100 #
1"
#3000
0"
#3500
b1000 !
b1000 #
1"
#4000
0"
#4500
b10000 !
b10000 #
1"
#5000
0"
#5500
b100000 !
b100000 #
1"
#6000
0"
#6500
b1000000 !
b1000000 #
1"
#7000
0"
#7500
b10000000 !
b10000000 #
1"
#8000
0"
#8500
b1 !
b1 #
1"
#9000
0"
#9500
b10 !
b10 #
1"
#10000
0"
#10500
b100 !
b100 #
1"
#11000
0"
#11500
b1000 !
b1000 #
1"
#12000
0"
#12500
b10000 !
b10000 #
1"
#13000
0"
#13500
b100000 !
b100000 #
1"
#14000
0"
#14500
b1000000 !
b1000000 #
1"
#15000
0"
#15500
b10000000 !
b10000000 #
1"
#16000
0"
#16500
b1 !
b1 #
1"
#17000
0"
#17500
b10 !
b10 #
1"
#18000
0"
#18500
b100 !
b100 #
1"
#19000
0"
#19500
b1000 !
b1000 #
1"
