syncupdowncounter.v
module syncupdowncounter(input clk,mode, output reg [3:0]y);
    initial begin
        y=4'b0001;
    end
    always @ (posedge clk)
     begin
        if (mode)
        begin
            y<=y+1;
        end
        else if (mode==1 && y==4'b1111)
        begin
            y<=4'b0000;
        end
        else if(!mode && y==4'b0000)
        begin 
            y<=4'b1111;
        end
        else
        begin
            y<=y-1;
        end
    end
 
endmodule

syncupdowncounter_tb.v
`timescale 1ns/1ps
module syncupdowncounter_tb;
    reg clk, mode;
    wire [3:0] y;

    syncupdowncounter s1 (
        .clk(clk),
        .mode(mode),
        .y(y)
    );

    initial begin
        $dumpfile("syncupdowncounter_tb.vcd");
        $dumpvars(0, syncupdowncounter_tb);
        $monitor(" mode = %b, y = %b", mode, y);
        clk = 0;
        mode = 0;
        #150 mode = 1;
        #150 mode = 0;
        #150 $finish;
    end
    always #5 clk <= ~clk;
endmodule

syncupdowncounter_tb.vcd
$date
	Fri May 08 14:27:39 2026
$end
$version
	Icarus Verilog
$end
$timescale
	1ps
$end
$scope module syncupdowncounter_tb $end
$var wire 4 ! y [3:0] $end
$var reg 1 " clk $end
$var reg 1 # mode $end
$scope module s1 $end
$var wire 1 " clk $end
$var wire 1 # mode $end
$var reg 4 $ y [3:0] $end
$upscope $end
$upscope $end
$enddefinitions $end
$comment Show the parameter values. $end
$dumpall
$end
#0
$dumpvars
b1 $
0#
0"
b1 !
$end
#5000
b0 !
b0 $
1"
#10000
0"
#15000
b1111 !
b1111 $
1"
#20000
0"
#25000
b1110 !
b1110 $
1"
#30000
0"
#35000
b1101 !
b1101 $
1"
#40000
0"
#45000
b1100 !
b1100 $
1"
#50000
0"
#55000
b1011 !
b1011 $
1"
#60000
0"
#65000
b1010 !
b1010 $
1"
#70000
0"
#75000
b1001 !
b1001 $
1"
#80000
0"
#85000
b1000 !
b1000 $
1"
#90000
0"
#95000
b111 !
b111 $
1"
#100000
0"
#105000
b110 !
b110 $
1"
#110000
0"
#115000
b101 !
b101 $
1"
#120000
0"
#125000
b100 !
b100 $
1"
#130000
0"
#135000
b11 !
b11 $
1"
#140000
0"
#145000
b10 !
b10 $
1"
#150000
0"
1#
#155000
b11 !
b11 $
1"
#160000
0"
#165000
b100 !
b100 $
1"
#170000
0"
#175000
b101 !
b101 $
1"
#180000
0"
#185000
b110 !
b110 $
1"
#190000
0"
#195000
b111 !
b111 $
1"
#200000
0"
#205000
b1000 !
b1000 $
1"
#210000
0"
#215000
b1001 !
b1001 $
1"
#220000
0"
#225000
b1010 !
b1010 $
1"
#230000
0"
#235000
b1011 !
b1011 $
1"
#240000
0"
#245000
b1100 !
b1100 $
1"
#250000
0"
#255000
b1101 !
b1101 $
1"
#260000
0"
#265000
b1110 !
b1110 $
1"
#270000
0"
#275000
b1111 !
b1111 $
1"
#280000
0"
#285000
b0 !
b0 $
1"
#290000
0"
#295000
b1 !
b1 $
1"
#300000
0"
0#
#305000
b0 !
b0 $
1"
#310000
0"
#315000
b1111 !
b1111 $
1"
#320000
0"
#325000
b1110 !
b1110 $
1"
#330000
0"
#335000
b1101 !
b1101 $
1"
#340000
0"
#345000
b1100 !
b1100 $
1"
#350000
0"
#355000
b1011 !
b1011 $
1"
#360000
0"
#365000
b1010 !
b1010 $
1"
#370000
0"
#375000
b1001 !
b1001 $
1"
#380000
0"
#385000
b1000 !
b1000 $
1"
#390000
0"
#395000
b111 !
b111 $
1"
#400000
0"
#405000
b110 !
b110 $
1"
#410000
0"
#415000
b101 !
b101 $
1"
#420000
0"
#425000
b100 !
b100 $
1"
#430000
0"
#435000
b11 !
b11 $
1"
#440000
0"
#445000
b10 !
b10 $
1"
